linqit/__init__.py
linqit/linq_list.py
tests/__init__.py
tests/test_list.py
linqit-0.1.5.dist-info/LICENSE
linqit-0.1.5.dist-info/METADATA
linqit-0.1.5.dist-info/WHEEL
linqit-0.1.5.dist-info/top_level.txt
linqit-0.1.5.dist-info/RECORD
