Metadata-Version: 2.1
Name: linqit
Version: 0.1.5
Summary: Extends python's list builtin with fun, robust functionality - .NET's Language Integrated Queries (Linq) and more. Write clean code with powerful syntax.
Home-page: https://github.com/avilum/linqit
Author: Avi Lumelsky
Author-email: noticetheg@gmail.com
Classifier: Programming Language :: Python :: 2
Classifier: Programming Language :: Python :: 3
Classifier: License :: OSI Approved :: Apache Software License
Classifier: Operating System :: OS Independent
Requires-Python: >=2.7,>=3.6
License-File: LICENSE
